pacifica_archiveinterface-0.4.2-py3.10-nspkg.pth
pacifica/archiveinterface/__init__.py
pacifica/archiveinterface/__main__.py
pacifica/archiveinterface/archive_utils.py
pacifica/archiveinterface/config.py
pacifica/archiveinterface/exception.py
pacifica/archiveinterface/globals.py
pacifica/archiveinterface/id2filename.py
pacifica/archiveinterface/rest_generator.py
pacifica/archiveinterface/wsgi.py
pacifica/archiveinterface/backends/__init__.py
pacifica/archiveinterface/backends/factory.py
pacifica/archiveinterface/backends/abstract/__init__.py
pacifica/archiveinterface/backends/abstract/archive.py
pacifica/archiveinterface/backends/abstract/status.py
pacifica/archiveinterface/backends/hpss/__init__.py
pacifica/archiveinterface/backends/hpss/archive.py
pacifica/archiveinterface/backends/hpss/extended.py
pacifica/archiveinterface/backends/hpss/status.py
pacifica/archiveinterface/backends/oracle_hsm_sideband/__init__.py
pacifica/archiveinterface/backends/oracle_hsm_sideband/archive.py
pacifica/archiveinterface/backends/oracle_hsm_sideband/extended_file_factory.py
pacifica/archiveinterface/backends/oracle_hsm_sideband/orm.py
pacifica/archiveinterface/backends/oracle_hsm_sideband/status.py
pacifica/archiveinterface/backends/posix/__init__.py
pacifica/archiveinterface/backends/posix/archive.py
pacifica/archiveinterface/backends/posix/extendedfile.py
pacifica/archiveinterface/backends/posix/status.py
tests/__init__.py
tests/admin_cmd_test.py
tests/cherrypy_test.py
tests/common_setup_test.py
tests/extended_test.py
tests/interface_test.py
tests/posix_failure_test.py
tests/posix_test.py
pacifica_archiveinterface-0.4.2.dist-info/AUTHORS
pacifica_archiveinterface-0.4.2.dist-info/LICENSE
pacifica_archiveinterface-0.4.2.dist-info/METADATA
pacifica_archiveinterface-0.4.2.dist-info/WHEEL
pacifica_archiveinterface-0.4.2.dist-info/entry_points.txt
pacifica_archiveinterface-0.4.2.dist-info/namespace_packages.txt
pacifica_archiveinterface-0.4.2.dist-info/top_level.txt
pacifica_archiveinterface-0.4.2.dist-info/RECORD
