Metadata-Version: 2.1
Name: pacifica-archiveinterface
Version: 0.4.2
Summary: Pacifica Archive Interface
Home-page: https://github.com/pacifica/pacifica-archiveinterface/
Author: David Brown
Author-email: david.brown@pnnl.gov
License-File: LICENSE
License-File: AUTHORS
Requires-Dist: cherrypy
Requires-Dist: peewee (>2)
Requires-Dist: PyMySQL
